setup.py
ledger_utility/__init__.py
ledger_utility/_version.py
ledger_utility/ledger_calc.py
ledger_utility/ledger_move.py
ledger_utility.egg-info/PKG-INFO
ledger_utility.egg-info/SOURCES.txt
ledger_utility.egg-info/dependency_links.txt
ledger_utility.egg-info/entry_points.txt
ledger_utility.egg-info/requires.txt
ledger_utility.egg-info/top_level.txt