Metadata-Version: 1.0
Name: ledger-utility
Version: 0.0.6
Summary: Ledger utility
Home-page: UNKNOWN
Author: eayin2
Author-email: eayin2@gmail.com
License: UNKNOWN
Platform: UNKNOWN
